a3dgamemaker-0.0.9.dist-info/licenses/licence
games/__init__.py
games/games.py
a3dgamemaker-0.0.9.dist-info/METADATA
a3dgamemaker-0.0.9.dist-info/WHEEL
a3dgamemaker-0.0.9.dist-info/top_level.txt
a3dgamemaker-0.0.9.dist-info/RECORD
