Metadata-Version: 2.4
Name: a3dgamemaker
Version: 0.0.9
Summary: create a 3d game in 10 lines (without map)
Author-email: delogstudio <3bth5550@gmail.com>
License: Proprietary
License-File: licence
Dynamic: license-file
